flask_back/__init__.py
flask_back/_version.py
flask_back-1.1.2.dist-info/licenses/LICENSE
flask_back-1.1.2.dist-info/METADATA
flask_back-1.1.2.dist-info/WHEEL
flask_back-1.1.2.dist-info/top_level.txt
flask_back-1.1.2.dist-info/RECORD
