Metadata-Version: 2.4
Name: flask_back
Version: 1.1.2
Summary: A lightweight Flask extension for managing back URLs
Author-email: Hcha Byte <Hcha.Byte@gmail.com>
License: MIT
Project-URL: Homepage, https://github.com/Hcha-byte/Flask-Back
Project-URL: Bug Tracker, https://github.com/Hcha-byte/Flask-Back/issues
Classifier: Framework :: Flask
Classifier: Programming Language :: Python :: 3
Classifier: License :: OSI Approved :: MIT License
Classifier: Operating System :: OS Independent
Requires-Python: >=3.7
License-File: LICENSE
Requires-Dist: Flask>=2.0
Provides-Extra: dev
Requires-Dist: pytest; extra == "dev"
Requires-Dist: pytest-cov; extra == "dev"
Dynamic: license-file
